PhasorMicroscopy/__init__.py
PhasorMicroscopy/funciones.py
PhasorMicroscopy-0.0.2.dist-info/METADATA
PhasorMicroscopy-0.0.2.dist-info/WHEEL
PhasorMicroscopy-0.0.2.dist-info/top_level.txt
PhasorMicroscopy-0.0.2.dist-info/RECORD
