Metadata-Version: 2.1
Name: PhasorMicroscopy
Version: 0.0.2
Summary: This is a library to performe phasor analysis in microscopy images
Home-page: https://github.com/bschuty
Author: Bruno Schuty Teske
Author-email: schutyteske@gmail.com
License: MIT
Platform: UNKNOWN
Requires-Dist: matplotlib
Requires-Dist: numpy
Requires-Dist: scikit-image
Requires-Dist: tifffile
